setup.cfg
setup.py
bin/cuts
cuts/__init__.py
cuts/bytes.py
cuts/chars.py
cuts/cutter.py
cuts/fields.py
cuts/main.py
cuts.egg-info/PKG-INFO
cuts.egg-info/SOURCES.txt
cuts.egg-info/dependency_links.txt
cuts.egg-info/top_level.txt