Metadata-Version: 1.1
Name: cuts
Version: 0.37.5
Summary: Remove and/or rearrange sections from each line of a file(s).
Home-page: https://github.com/jpweiser/cuts
Author: J.P. Weiser
Author-email: jon@jpweiser.com
License: UNKNOWN
Download-URL: https://github.com/jpweiser/cuts/tarball/master
Platform: UNKNOWN
Classifier: Environment :: Console
Classifier: License :: OSI Approved :: GNU General Public License v3 (GPLv3)
Classifier: Operating System :: POSIX
Classifier: Operating System :: POSIX :: BSD :: BSD/OS
Classifier: Operating System :: POSIX :: BSD :: FreeBSD
Classifier: Operating System :: POSIX :: Linux
Classifier: Operating System :: POSIX :: Other
Classifier: Operating System :: Unix
Classifier: Programming Language :: Python
Classifier: Programming Language :: Python :: 2.7
Classifier: Programming Language :: Python :: 3
Classifier: Programming Language :: Python :: 3.4
Classifier: Topic :: Text Editors
Classifier: Topic :: Text Editors :: Documentation
Classifier: Topic :: Text Editors :: Text Processing
Classifier: Topic :: Text Processing :: Filters
Classifier: Topic :: Text Processing :: General
Classifier: Topic :: Utilities
